HardwareMonitor/Util.py
HardwareMonitor/__init__.py
HardwareMonitor/Hardware/__init__.py
HardwareMonitor/Hardware/__init__.pyi
HardwareMonitor/Hardware/CPU/__init__.py
HardwareMonitor/Hardware/CPU/__init__.pyi
HardwareMonitor/Hardware/Controller/__init__.py
HardwareMonitor/Hardware/Controller/AeroCool/__init__.py
HardwareMonitor/Hardware/Controller/AeroCool/__init__.pyi
HardwareMonitor/Hardware/Controller/AquaComputer/__init__.py
HardwareMonitor/Hardware/Controller/AquaComputer/__init__.pyi
HardwareMonitor/Hardware/Gpu/__init__.py
HardwareMonitor/Hardware/Gpu/__init__.pyi
HardwareMonitor/Hardware/Motherboard/__init__.py
HardwareMonitor/Hardware/Motherboard/__init__.pyi
HardwareMonitor/Hardware/Motherboard/Lpc/__init__.py
HardwareMonitor/Hardware/Motherboard/Lpc/EC/__init__.py
HardwareMonitor/Hardware/Motherboard/Lpc/EC/__init__.pyi
HardwareMonitor/Hardware/Psu/__init__.py
HardwareMonitor/Hardware/Psu/Corsair/__init__.py
HardwareMonitor/Hardware/Psu/Corsair/__init__.pyi
HardwareMonitor/Hardware/Storage/__init__.py
HardwareMonitor/Hardware/Storage/__init__.pyi
HardwareMonitor/Interop/__init__.py
HardwareMonitor/Interop/__init__.pyi
HardwareMonitor/PawnIo/__init__.py
HardwareMonitor/PawnIo/__init__.pyi
HardwareMonitor/Software/__init__.py
HardwareMonitor/Software/__init__.pyi
HardwareMonitor/_util/types.pyi
HardwareMonitor/lib/HidSharp.dll
HardwareMonitor/lib/LICENSE
HardwareMonitor/lib/LibreHardwareMonitorLib.dll
HardwareMonitor/lib/RAMSPDToolkit-NDD.dll
hardwaremonitor-1.1.0.dist-info/licenses/LICENSE
hardwaremonitor-1.1.0.dist-info/METADATA
hardwaremonitor-1.1.0.dist-info/WHEEL
hardwaremonitor-1.1.0.dist-info/top_level.txt
hardwaremonitor-1.1.0.dist-info/RECORD
