Metadata-Version: 2.4
Name: HardwareMonitor
Version: 1.1.0
Summary: Python import layer for the LibreHardwareMonitorLib assembly.
Author-email: Nicholas Feix <nf@fconsoft.com>
License: BSD 3-Clause License
Project-URL: Repository, https://github.com/snip3rnick/PyHardwareMonitor
Keywords: monitoring,sensors,LibreHardwareMonitor
Classifier: License :: Other/Proprietary License
Classifier: Intended Audience :: Developers
Classifier: Environment :: Win32 (MS Windows)
Classifier: Programming Language :: Python
Classifier: Programming Language :: Python :: 3
Classifier: Topic :: System :: Monitoring
Requires-Python: >=3.6
License-File: LICENSE
Requires-Dist: pythonnet
Dynamic: license-file
